doc_gen/__init__.py
doc_gen/cli.py
doc_gen/app/__init__.py
doc_gen/app/main.py
doc_gen/app/pages/__init__.py
doc_gen/app/pages/about.py
doc_gen/app/pages/generator.py
doc_gen/app/static/background.jpg
doc_gen/core/__init__.py
doc_gen/core/error_handler.py
doc_gen/core/orchestrator.py
doc_gen/core/renderer.py
doc_gen/core/parsers/__init__.py
doc_gen/core/parsers/base.py
doc_gen/core/parsers/c.py
doc_gen/core/parsers/java.py
doc_gen/templates/report_c.md
doc_gen/templates/report_java.md
doc_gen_pro-0.1.1.dist-info/METADATA
doc_gen_pro-0.1.1.dist-info/WHEEL
doc_gen_pro-0.1.1.dist-info/entry_points.txt
doc_gen_pro-0.1.1.dist-info/RECORD
