Metadata-Version: 2.4
Name: doc-gen-pro
Version: 0.1.1
Summary: 一个支持多语言的源代码文档生成器。
Author-email: JFeng2048 <JFeng2048@zohomail.cn>
Maintainer-email: JFeng2048 <JFeng2048@zohomail.cn>
License: MIT
Keywords: documentation,generator,mermaid,source-code,streamlit,代码文档,文档生成器,源代码
Classifier: Development Status :: 4 - Beta
Classifier: Intended Audience :: Developers
Classifier: License :: OSI Approved :: MIT License
Classifier: Operating System :: OS Independent
Classifier: Programming Language :: Python :: 3
Classifier: Programming Language :: Python :: 3.9
Classifier: Programming Language :: Python :: 3.10
Classifier: Programming Language :: Python :: 3.11
Classifier: Programming Language :: Python :: 3.12
Classifier: Programming Language :: Python :: 3.13
Classifier: Topic :: Software Development :: Documentation
Classifier: Topic :: Software Development :: Libraries :: Python Modules
Requires-Python: <3.14,>=3.9
Requires-Dist: jinja2>=3.1.0
Requires-Dist: streamlit-mermaid>=0.3.0
Requires-Dist: streamlit>=1.28.0
Provides-Extra: dev
Requires-Dist: black>=23.0.0; extra == 'dev'
Requires-Dist: flake8>=6.0.0; extra == 'dev'
Requires-Dist: isort>=5.12.0; extra == 'dev'
Requires-Dist: mypy>=1.5.0; extra == 'dev'
Requires-Dist: pytest-cov>=4.0.0; extra == 'dev'
Requires-Dist: pytest>=8.4.2; extra == 'dev'
